MicrobeRX-0.3.2.data/scripts/microberx_cli.py
microberx/DataFiles.py
microberx/MetaboliteAnalyzer.py
microberx/MetabolitePredictor.py
microberx/MetaboliteVisualizer.py
microberx/OmicsIntegrator.py
microberx/RuleGenerator.py
microberx/__init__.py
microberx/_version.py
microberx/.ipynb_checkpoints/DataFiles-checkpoint.py
microberx/.ipynb_checkpoints/OmicsIntegrator-checkpoint.py
microberx/DataBase/Evidences.tsv.gz
microberx/DataBase/MicrobesData.tsv.gz
microberx/DataBase/MicrobesReactions.tsv.gz
microberx/DataBase/ReactionRules.tsv.gz
microberx/bin/RTD.jar
microberx/bin/RTD_LICENSE
microberx/bin/clustalw2
MicrobeRX-0.3.2.dist-info/LICENSE
MicrobeRX-0.3.2.dist-info/METADATA
MicrobeRX-0.3.2.dist-info/WHEEL
MicrobeRX-0.3.2.dist-info/entry_points.txt
MicrobeRX-0.3.2.dist-info/top_level.txt
MicrobeRX-0.3.2.dist-info/RECORD
