Metadata-Version: 2.1
Name: MicrobeRX
Version: 0.3.2
Summary: MicrobeRX is A tool for enzymatic reaction-based metabolite prediction in the gut microbiome.
Home-page: https://github.com/GRONINGEN-MICROBIOME-CENTRE/MicrobeRX
Download-URL: https://github.com/GRONINGEN-MICROBIOME-CENTRE/MicrobeRX
Author: GRONINGEN-MICROBIOME-CENTRE (Angel J. Ruiz-Moreno)
Author-email: <angel.j.ruiz.moreno@gmail.com>
Keywords: python,metabolite,prediction,microbiome,cheminformatics,metabolism
Classifier: Development Status :: 1 - Planning
Classifier: Intended Audience :: Science/Research
Classifier: License :: OSI Approved :: GNU General Public License v3 (GPLv3)
Classifier: Topic :: Scientific/Engineering :: Bio-Informatics
Classifier: Topic :: Scientific/Engineering :: Chemistry
Classifier: Programming Language :: Python :: 3
Classifier: Operating System :: Unix
Classifier: Operating System :: MacOS :: MacOS X
Classifier: Operating System :: Microsoft :: Windows
Requires-Python: >=3.8
License-File: LICENSE
Requires-Dist: importlib-resources
Requires-Dist: datamol
Requires-Dist: distinctipy
Requires-Dist: kaleido
Requires-Dist: mols2grid
Requires-Dist: pandas
Requires-Dist: plotly
Requires-Dist: PubChemPy
Requires-Dist: pyopenms
Requires-Dist: rdkit
Requires-Dist: biopython
Requires-Dist: rxnmapper
Requires-Dist: scikit-learn
Requires-Dist: scipy
Requires-Dist: seaborn
Requires-Dist: tqdm
Requires-Dist: dash
Requires-Dist: jupyter-dash
Requires-Dist: dash-bio
Requires-Dist: microberx
